eodh_jpyauth/__init__.py
eodh_jpyauth/auth.py
eodh_jpyauth/spawners.py
eodh_jpyauth-0.1.3.dist-info/METADATA
eodh_jpyauth-0.1.3.dist-info/WHEEL
eodh_jpyauth-0.1.3.dist-info/RECORD
