Metadata-Version: 2.4
Name: eodh-jpyauth
Version: 0.1.3
Summary: A JupyterHub OIDC authenticator for Keycloak
Author-email: Steven Gillies <steven.gillies@telespazio.com>
Requires-Python: >=3.10
Requires-Dist: jupyterhub-kubespawner>=7.0.0
Requires-Dist: oauthenticator>=17.3.0
